docr/__init__.py
docr/cmdline.py
docr/config/__init__.py
docr/config/settings.yml
docr/config/settings1.py
docr/core/__init__.py
docr/core/base/__init__.py
docr/core/base/model.py
docr/core/detection/__init__.py
docr/core/detection/dbnet.py
docr/core/detection/lore.py
docr/core/detection/yolov8 copy.py
docr/core/detection/yolov8.py
docr/core/reading_order/__init__.py
docr/core/reading_order/xycut.py
docr/core/recognition/__init__.py
docr/core/recognition/crnn.py
docr/core/recognition/latexocr.py
docr/data/__init__.py
docr/data/types.py
docr/log.py
docr/modules/__init__.py
docr/modules/base.py
docr/modules/detformula.py
docr/modules/layout.py
docr/modules/ocr.py
docr/modules/table.py
docr/utils/__init__.py
docr/utils/input.py
docr/utils/visual.py
docr-0.2.1.dist-info/LICENSE
docr-0.2.1.dist-info/METADATA
docr-0.2.1.dist-info/WHEEL
docr-0.2.1.dist-info/entry_points.txt
docr-0.2.1.dist-info/RECORD
