Metadata-Version: 2.1
Name: docr
Version: 0.2.1
Summary: 🛠️ Docr: A modular toolkit for intelligent document analysis and processing. Easy to expand and flexible to use, just like playing with building blocks!
License: MIT
Author: liferecords
Author-email: yjmm10@yeah.net
Requires-Python: >=3.10,<4.0
Classifier: License :: OSI Approved :: MIT License
Classifier: Operating System :: OS Independent
Classifier: Programming Language :: Python :: 3
Classifier: Programming Language :: Python :: 3.10
Classifier: Programming Language :: Python :: 3.11
Classifier: Programming Language :: Python :: 3.12
Requires-Dist: click (>=8.1.3,<9.0.0)
Requires-Dist: dynaconf (>=3.1.12,<4.0.0)
Requires-Dist: fastapi (>=0.112.0,<0.113.0)
Requires-Dist: onnxruntime (>=1.18.1,<2.0.0)
Requires-Dist: opencv-python (>=4.10.0.84,<5.0.0.0)
Requires-Dist: pillow (>=10.4.0,<11.0.0)
Requires-Dist: psutil (>=6.0.0,<7.0.0)
Requires-Dist: pyclipper (>=1.3.0.post5,<2.0.0)
Requires-Dist: pydantic (>=2.8.2,<3.0.0)
Requires-Dist: pymupdf (>=1.24.9,<2.0.0)
Requires-Dist: python-multipart (>=0.0.9,<0.0.10)
Requires-Dist: shapely (>=2.0.5,<3.0.0)
Requires-Dist: streamlit (>=1.37.1,<2.0.0)
Requires-Dist: tokenizers (>=0.19.1,<0.20.0)
Requires-Dist: uvicorn[standard] (>=0.30.5,<0.31.0)
